slashpatch/__init__.py
slashpatch/command.py
slashpatch/context.py
slashpatch/objects.py
slashpatch/server.py
slashpatch-1.1.0.dist-info/LICENSE
slashpatch-1.1.0.dist-info/METADATA
slashpatch-1.1.0.dist-info/WHEEL
slashpatch-1.1.0.dist-info/top_level.txt
slashpatch-1.1.0.dist-info/RECORD
