Metadata-Version: 2.1
Name: slashpatch
Version: 1.1.0
Summary: A command handler/dispatcher webserver for Discord slash commands
Home-page: https://github.com/vcokltfre/slashpatch
Author: vcokltfre
Author-email: vcokltfre@gmail.com
License: UNKNOWN
Project-URL: Bug Tracker, https://github.com/vcokltfre/slashpatch/issues
Platform: UNKNOWN
Classifier: Programming Language :: Python :: 3
Classifier: License :: OSI Approved :: MIT License
Classifier: Operating System :: OS Independent
Requires-Python: >=3.8
